cleared/__init__.py
cleared/cli/__init__.py
cleared/cli/cmds/__init__.py
cleared/cli/cmds/check_syntax.py
cleared/cli/cmds/describe.py
cleared/cli/cmds/format.py
cleared/cli/cmds/info.py
cleared/cli/cmds/init.py
cleared/cli/cmds/lint.py
cleared/cli/cmds/report_verify.py
cleared/cli/cmds/reverse.py
cleared/cli/cmds/run.py
cleared/cli/cmds/setup.py
cleared/cli/cmds/test.py
cleared/cli/cmds/validate.py
cleared/cli/cmds/verify/__init__.py
cleared/cli/cmds/verify/core.py
cleared/cli/cmds/verify/model.py
cleared/cli/cmds/verify/utils.py
cleared/cli/main.py
cleared/cli/templates/describe/report.html.j2
cleared/cli/templates/report_verify/report.html.j2
cleared/cli/utils.py
cleared/config/__init__.py
cleared/config/structure.py
cleared/engine.py
cleared/io/__init__.py
cleared/io/base.py
cleared/io/filesystem.py
cleared/io/sql.py
cleared/lint/__init__.py
cleared/lint/core.py
cleared/lint/rules/__init__.py
cleared/lint/rules/complexity.py
cleared/lint/rules/dependencies.py
cleared/lint/rules/format.py
cleared/lint/rules/io.py
cleared/lint/rules/timeshift.py
cleared/lint/rules/transformers.py
cleared/lint/rules/uniqueness.py
cleared/lint/rules/validation.py
cleared/lint/types.py
cleared/lint/utils.py
cleared/logging_config.py
cleared/models/__init__.py
cleared/models/verify_models.py
cleared/sample.py
cleared/transformers/__init__.py
cleared/transformers/base.py
cleared/transformers/id.py
cleared/transformers/pipelines.py
cleared/transformers/registry.py
cleared/transformers/simple.py
cleared/transformers/temporal.py
cleared-0.4.11.dist-info/METADATA
cleared-0.4.11.dist-info/WHEEL
cleared-0.4.11.dist-info/entry_points.txt
cleared-0.4.11.dist-info/licenses/LICENSE
cleared-0.4.11.dist-info/RECORD
