Metadata-Version: 2.4
Name: cleared
Version: 0.4.11
Summary: An open-source multi-purpose de-identification library with special support for healthcare applications. Provides robust tools to de-identify multi-table, multimodal datasets while maintaining clinical integrity and research utility.
License: Apache-2.0 with Commons Clause restriction
License-File: LICENSE
Keywords: de-identification,healthcare,privacy,data-protection,hipaa,gdpr
Author: NOMA AI INC.
Requires-Python: >=3.10,<3.14
Classifier: Development Status :: 3 - Alpha
Classifier: Intended Audience :: Healthcare Industry
Classifier: Intended Audience :: Science/Research
Classifier: License :: Other/Proprietary License
Classifier: Programming Language :: Python :: 3
Classifier: Programming Language :: Python :: 3.10
Classifier: Programming Language :: Python :: 3.11
Classifier: Programming Language :: Python :: 3.12
Classifier: Programming Language :: Python :: 3.13
Classifier: Topic :: Scientific/Engineering :: Medical Science Apps.
Requires-Dist: colorlog (>=6.8.0)
Requires-Dist: hydra-core (>=1.3.2)
Requires-Dist: jinja2 (>=3.1.2)
Requires-Dist: networkx (>=3.0)
Requires-Dist: pandas (>=2.3.3)
Requires-Dist: presidio-analyzer (>=2.2.359)
Requires-Dist: presidio-anonymizer (>=2.2.359)
Requires-Dist: psycopg2-binary (>=2.9.11)
Requires-Dist: ruamel-yaml (>=0.18.0)
Requires-Dist: sqlalchemy (>=2.0.44)
Requires-Dist: tomli (>=2.0.1) ; python_version < "3.11"
Requires-Dist: typer (>=0.19.2)
Requires-Dist: yamllint (>=1.37.1)
Project-URL: Homepage, https://github.com/nomaai/cleared
Project-URL: Repository, https://github.com/nomaai/cleared
